{"v":"5.9.0","fr":25,"ip":0,"op":60,"w":400,"h":813,"nm":"Type","ddd":0,"assets":[],"layers":[{"ddd":0,"ind":1,"ty":4,"nm":"Layer 5 Outlines","sr":1,"ks":{"o":{"a":0,"k":100,"ix":11},"r":{"a":0,"k":0,"ix":10},"p":{"a":1,"k":[{"i":{"x":0,"y":1},"o":{"x":0.5,"y":0},"t":0,"s":[117.378,180.585,0],"to":[0,0,0],"ti":[0,0,0]},{"i":{"x":0,"y":1},"o":{"x":0.5,"y":0},"t":30,"s":[126.978,180.585,0],"to":[0,0,0],"ti":[0,0,0]},{"t":60,"s":[117.378,180.585,0]}],"ix":2,"l":2},"a":{"a":0,"k":[114.576,124.431,0],"ix":1,"l":2},"s":{"a":0,"k":[96,96,100],"ix":6,"l":2}},"ao":0,"shapes":[{"ty":"gr","it":[{"ind":0,"ty":"sh","ix":1,"ks":{"a":1,"k":[{"i":{"x":0,"y":1},"o":{"x":0.5,"y":0},"t":0,"s":[{"i":[[0,0],[0,0],[0,0]],"o":[[0,0],[0,0],[0,0]],"v":[[31.538,29.567],[-0.001,-61.105],[-31.539,29.567]],"c":true}]},{"i":{"x":0,"y":1},"o":{"x":0.5,"y":0},"t":30,"s":[{"i":[[0,0],[0,0],[0,0]],"o":[[0,0],[0,0],[0,0]],"v":[[41.395,39.423],[-9.856,-92.642],[-61.105,39.423]],"c":true}]},{"t":60,"s":[{"i":[[0,0],[0,0],[0,0]],"o":[[0,0],[0,0],[0,0]],"v":[[31.538,29.567],[-0.001,-61.105],[-31.539,29.567]],"c":true}]}],"ix":2},"nm":"Path 1","mn":"ADBE Vector Shape - Group","hd":false},{"ind":1,"ty":"sh","ix":2,"ks":{"a":1,"k":[{"i":{"x":0,"y":1},"o":{"x":0.5,"y":0},"t":0,"s":[{"i":[[0,0],[0,0],[0,0],[0,0],[0,0],[0,0],[0,0],[0,0]],"o":[[0,0],[0,0],[0,0],[0,0],[0,0],[0,0],[0,0],[0,0]],"v":[[-21.684,-124.181],[21.683,-124.181],[114.326,124.181],[65.047,124.181],[47.307,72.932],[-47.309,72.932],[-65.049,124.181],[-114.326,124.181]],"c":true}]},{"i":{"x":0,"y":1},"o":{"x":0.5,"y":0},"t":30,"s":[{"i":[[0,0],[0,0],[0,0],[0,0],[0,0],[0,0],[0,0],[0,0]],"o":[[0,0],[0,0],[0,0],[0,0],[0,0],[0,0],[0,0],[0,0]],"v":[[-17.741,-124.181],[-1.971,-124.181],[94.615,124.182],[72.934,124.182],[47.307,57.163],[-67.019,57.163],[-92.643,124.182],[-114.326,124.182]],"c":true}]},{"t":60,"s":[{"i":[[0,0],[0,0],[0,0],[0,0],[0,0],[0,0],[0,0],[0,0]],"o":[[0,0],[0,0],[0,0],[0,0],[0,0],[0,0],[0,0],[0,0]],"v":[[-21.684,-124.181],[21.683,-124.181],[114.326,124.181],[65.047,124.181],[47.307,72.932],[-47.309,72.932],[-65.049,124.181],[-114.326,124.181]],"c":true}]}],"ix":2},"nm":"Path 2","mn":"ADBE Vector Shape - Group","hd":false},{"ty":"mm","mm":1,"nm":"Merge Paths 1","mn":"ADBE Vector Filter - Merge","hd":false},{"ty":"fl","c":{"a":0,"k":[1,1,1,1],"ix":4},"o":{"a":0,"k":100,"ix":5},"r":1,"bm":0,"nm":"Fill 1","mn":"ADBE Vector Graphic - Fill","hd":false},{"ty":"tr","p":{"a":0,"k":[114.576,124.431],"ix":2},"a":{"a":0,"k":[0,0],"ix":1},"s":{"a":0,"k":[100,100],"ix":3},"r":{"a":0,"k":0,"ix":6},"o":{"a":0,"k":100,"ix":7},"sk":{"a":0,"k":0,"ix":4},"sa":{"a":0,"k":0,"ix":5},"nm":"Transform"}],"nm":"Group 1","np":4,"cix":2,"bm":0,"ix":1,"mn":"ADBE Vector Group","hd":false}],"ip":0,"op":60,"st":0,"bm":0},{"ddd":0,"ind":2,"ty":4,"nm":"Layer 3 Outlines","sr":1,"ks":{"o":{"a":0,"k":100,"ix":11},"r":{"a":0,"k":0,"ix":10},"p":{"a":1,"k":[{"i":{"x":0,"y":1},"o":{"x":0.5,"y":0},"t":0,"s":[107.68,621.772,0],"to":[0,0,0],"ti":[0,0,0]},{"i":{"x":0,"y":1},"o":{"x":0.5,"y":0},"t":30,"s":[117.28,621.772,0],"to":[0,0,0],"ti":[0,0,0]},{"t":60,"s":[107.68,621.772,0]}],"ix":2,"l":2},"a":{"a":0,"k":[93.879,124.432,0],"ix":1,"l":2},"s":{"a":0,"k":[96,96,100],"ix":6,"l":2}},"ao":0,"shapes":[{"ty":"gr","it":[{"ind":0,"ty":"sh","ix":1,"ks":{"a":1,"k":[{"i":{"x":0,"y":1},"o":{"x":0.5,"y":0},"t":0,"s":[{"i":[[0,0],[0,19.71],[21.683,0],[0,0],[0,0]],"o":[[21.683,0],[0,-19.712],[0,0],[0,0],[0,0]],"v":[[8.87,82.787],[46.322,47.307],[8.87,11.826],[-46.322,11.826],[-46.322,82.787]],"c":true}]},{"i":{"x":0,"y":1},"o":{"x":0.5,"y":0},"t":30,"s":[{"i":[[0,0],[0,27.596],[33.509,0],[0,0],[0,0]],"o":[[33.509,0],[0,-25.625],[0,0],[0,0],[0,0]],"v":[[-2.956,106.44],[56.178,53.219],[-2.956,1.97],[-73.917,1.97],[-73.917,106.44]],"c":true}]},{"t":60,"s":[{"i":[[0,0],[0,19.71],[21.683,0],[0,0],[0,0]],"o":[[21.683,0],[0,-19.712],[0,0],[0,0],[0,0]],"v":[[8.87,82.787],[46.322,47.307],[8.87,11.826],[-46.322,11.826],[-46.322,82.787]],"c":true}]}],"ix":2},"nm":"Path 1","mn":"ADBE Vector Shape - Group","hd":false},{"ind":1,"ty":"sh","ix":2,"ks":{"a":1,"k":[{"i":{"x":0,"y":1},"o":{"x":0.5,"y":0},"t":0,"s":[{"i":[[0,0],[0,15.77],[17.74,0],[0,0],[0,0]],"o":[[17.74,0],[0,-15.768],[0,0],[0,0],[0,0]],"v":[[4.928,-23.654],[36.467,-53.222],[4.928,-82.787],[-46.322,-82.787],[-46.322,-23.654]],"c":true}]},{"i":{"x":0,"y":1},"o":{"x":0.5,"y":0},"t":30,"s":[{"i":[[0,0],[0,25.624],[31.538,0],[0,0],[0,0]],"o":[[31.538,0],[0,-25.625],[0,0],[0,0],[0,0]],"v":[[-6.898,-15.77],[44.352,-61.106],[-6.898,-106.442],[-73.917,-106.442],[-73.917,-15.77]],"c":true}]},{"t":60,"s":[{"i":[[0,0],[0,15.77],[17.74,0],[0,0],[0,0]],"o":[[17.74,0],[0,-15.768],[0,0],[0,0],[0,0]],"v":[[4.928,-23.654],[36.467,-53.222],[4.928,-82.787],[-46.322,-82.787],[-46.322,-23.654]],"c":true}]}],"ix":2},"nm":"Path 2","mn":"ADBE Vector Shape - Group","hd":false},{"ind":2,"ty":"sh","ix":3,"ks":{"a":1,"k":[{"i":{"x":0,"y":1},"o":{"x":0.5,"y":0},"t":0,"s":[{"i":[[0,0],[0,0],[0,-37.452],[0,0],[0,-45.336],[47.308,0],[0,0]],"o":[[0,0],[43.365,0],[0,33.508],[0,0],[0,37.451],[0,0],[0,0]],"v":[[-93.629,-124.182],[8.87,-124.182],[83.773,-55.192],[54.206,-7.885],[93.629,53.221],[12.812,124.182],[-93.629,124.182]],"c":true}]},{"i":{"x":0,"y":1},"o":{"x":0.5,"y":0},"t":30,"s":[{"i":[[0,0],[0,0],[0,-35.48],[0,0],[0,-45.336],[47.307,0],[0,0]],"o":[[0,0],[43.364,0],[0,39.422],[0,0],[0,39.423],[0,0],[0,0]],"v":[[-93.629,-124.182],[-6.898,-124.182],[64.062,-61.106],[28.583,-7.886],[75.889,53.219],[-2.956,124.18],[-93.629,124.18]],"c":true}]},{"t":60,"s":[{"i":[[0,0],[0,0],[0,-37.452],[0,0],[0,-45.336],[47.308,0],[0,0]],"o":[[0,0],[43.365,0],[0,33.508],[0,0],[0,37.451],[0,0],[0,0]],"v":[[-93.629,-124.182],[8.87,-124.182],[83.773,-55.192],[54.206,-7.885],[93.629,53.221],[12.812,124.182],[-93.629,124.182]],"c":true}]}],"ix":2},"nm":"Path 3","mn":"ADBE Vector Shape - Group","hd":false},{"ty":"mm","mm":1,"nm":"Merge Paths 1","mn":"ADBE Vector Filter - Merge","hd":false},{"ty":"fl","c":{"a":0,"k":[1,1,1,1],"ix":4},"o":{"a":0,"k":100,"ix":5},"r":1,"bm":0,"nm":"Fill 1","mn":"ADBE Vector Graphic - Fill","hd":false},{"ty":"tr","p":{"a":0,"k":[93.879,124.432],"ix":2},"a":{"a":0,"k":[0,0],"ix":1},"s":{"a":0,"k":[100,100],"ix":3},"r":{"a":0,"k":0,"ix":6},"o":{"a":0,"k":100,"ix":7},"sk":{"a":0,"k":0,"ix":4},"sa":{"a":0,"k":0,"ix":5},"nm":"Transform"}],"nm":"Group 1","np":5,"cix":2,"bm":0,"ix":1,"mn":"ADBE Vector Group","hd":false}],"ip":0,"op":60,"st":0,"bm":0},{"ddd":0,"ind":3,"ty":4,"nm":"Layer 6 Outlines","sr":1,"ks":{"o":{"a":0,"k":100,"ix":11},"r":{"a":0,"k":0,"ix":10},"p":{"a":1,"k":[{"i":{"x":0,"y":1},"o":{"x":0.5,"y":0},"t":0,"s":[312.9,620.83,0],"to":[0,0,0],"ti":[0,0,0]},{"i":{"x":0,"y":1},"o":{"x":0.5,"y":0},"t":30,"s":[303.3,620.83,0],"to":[0,0,0],"ti":[0,0,0]},{"t":60,"s":[312.9,620.83,0]}],"ix":2,"l":2},"a":{"a":0,"k":[80.081,125.416,0],"ix":1,"l":2},"s":{"a":0,"k":[96,96,100],"ix":6,"l":2}},"ao":0,"shapes":[{"ty":"gr","it":[{"ind":0,"ty":"sh","ix":1,"ks":{"a":1,"k":[{"i":{"x":0,"y":1},"o":{"x":0.5,"y":0},"t":0,"s":[{"i":[[0,41.394],[33.509,0],[0,-41.395],[-33.51,0]],"o":[[0,-41.395],[-33.51,0],[0,41.394],[33.509,0]],"v":[[64.455,36.467],[1.379,-34.494],[-61.697,36.467],[1.379,107.426]],"c":true}]},{"i":{"x":0,"y":1},"o":{"x":0.5,"y":0},"t":30,"s":[{"i":[[0,29.566],[25.625,0],[0,-29.567],[-25.625,0]],"o":[[0,-29.567],[-25.625,0],[0,29.566],[25.625,0]],"v":[[54.598,32.524],[9.262,-16.754],[-36.074,32.524],[9.262,81.802]],"c":true}]},{"t":60,"s":[{"i":[[0,41.394],[33.509,0],[0,-41.395],[-33.51,0]],"o":[[0,-41.395],[-33.51,0],[0,41.394],[33.509,0]],"v":[[64.455,36.467],[1.379,-34.494],[-61.697,36.467],[1.379,107.426]],"c":true}]}],"ix":2},"nm":"Path 1","mn":"ADBE Vector Shape - Group","hd":false},{"ind":1,"ty":"sh","ix":2,"ks":{"a":1,"k":[{"i":{"x":0,"y":1},"o":{"x":0.5,"y":0},"t":0,"s":[{"i":[[0,0],[0,0],[0,0],[0,0],[0,0],[0,0],[0,0],[0,0],[-39.423,0],[0,-51.25],[45.336,0]],"o":[[0,0],[0,0],[0,0],[0,0],[0,0],[0,0],[0,0],[0,0],[45.336,0],[0,51.249],[-39.423,0]],"v":[[-57.756,93.629],[-59.727,93.629],[-65.64,123.196],[-77.467,123.196],[-77.467,-125.167],[-59.727,-125.167],[-59.727,-20.696],[-57.756,-20.696],[1.379,-52.234],[82.195,36.467],[1.379,125.167]],"c":true}]},{"i":{"x":0,"y":1},"o":{"x":0.5,"y":0},"t":30,"s":[{"i":[[0,0],[0,0],[0,0],[0,0],[0,0],[0,0],[0,0],[0,0],[-39.423,0],[1.135,-55.98],[35.589,0.323]],"o":[[0,0],[0,0],[0,0],[0,0],[0,0],[0,0],[0,0],[0,0],[45.336,0],[-1.227,60.523],[-39.421,-0.358]],"v":[[-36.006,105.129],[-35.477,105.129],[-45.39,123.446],[-77.467,123.196],[-77.467,-125.167],[-33.727,-125.239],[-32.477,-42.196],[-32.256,-41.946],[14.129,-59.984],[99.695,36.217],[15.379,124.417]],"c":true}]},{"t":60,"s":[{"i":[[0,0],[0,0],[0,0],[0,0],[0,0],[0,0],[0,0],[0,0],[-39.423,0],[0,-51.25],[45.336,0]],"o":[[0,0],[0,0],[0,0],[0,0],[0,0],[0,0],[0,0],[0,0],[45.336,0],[0,51.249],[-39.423,0]],"v":[[-57.756,93.629],[-59.727,93.629],[-65.64,123.196],[-77.467,123.196],[-77.467,-125.167],[-59.727,-125.167],[-59.727,-20.696],[-57.756,-20.696],[1.379,-52.234],[82.195,36.467],[1.379,125.167]],"c":true}]}],"ix":2},"nm":"Path 2","mn":"ADBE Vector Shape - Group","hd":false},{"ty":"mm","mm":1,"nm":"Merge Paths 1","mn":"ADBE Vector Filter - Merge","hd":false},{"ty":"fl","c":{"a":0,"k":[1,1,1,1],"ix":4},"o":{"a":0,"k":100,"ix":5},"r":1,"bm":0,"nm":"Fill 1","mn":"ADBE Vector Graphic - Fill","hd":false},{"ty":"tr","p":{"a":0,"k":[77.717,125.416],"ix":2},"a":{"a":0,"k":[0,0],"ix":1},"s":{"a":0,"k":[100,100],"ix":3},"r":{"a":0,"k":0,"ix":6},"o":{"a":0,"k":100,"ix":7},"sk":{"a":0,"k":0,"ix":4},"sa":{"a":0,"k":0,"ix":5},"nm":"Transform"}],"nm":"Group 1","np":4,"cix":2,"bm":0,"ix":1,"mn":"ADBE Vector Group","hd":false}],"ip":0,"op":60,"st":0,"bm":0},{"ddd":0,"ind":4,"ty":4,"nm":"Layer 8 Outlines","sr":1,"ks":{"o":{"a":0,"k":100,"ix":11},"r":{"a":0,"k":0,"ix":10},"p":{"a":0,"k":[311.285,216.538,0],"ix":2,"l":2},"a":{"a":0,"k":[68.254,88.951,0],"ix":1,"l":2},"s":{"a":0,"k":[96,96,100],"ix":6,"l":2}},"ao":0,"shapes":[{"ty":"gr","it":[{"ind":0,"ty":"sh","ix":1,"ks":{"a":1,"k":[{"i":{"x":0,"y":1},"o":{"x":0.5,"y":0},"t":0,"s":[{"i":[[0,33.509],[0,0],[0,0],[0,-21.683],[-29.568,0]],"o":[[0,0],[0,0],[-61.104,0],[0,15.769],[33.508,0]],"v":[[50.264,15.769],[50.264,0],[28.581,0],[-50.263,39.423],[-4.927,70.961]],"c":true}]},{"i":{"x":0,"y":1},"o":{"x":0.5,"y":0},"t":30,"s":[{"i":[[-0.228,25.608],[0,0],[0,0],[0.049,-19.546],[-15.786,-0.084]],"o":[[0,0],[0,0],[-38.044,-1.873],[-0.04,15.769],[21.967,0.117]],"v":[[31.764,9.019],[32.014,9.25],[31.081,8.75],[-31.513,31.423],[-4.677,53.211]],"c":true}]},{"t":60,"s":[{"i":[[0,33.509],[0,0],[0,0],[0,-21.683],[-29.568,0]],"o":[[0,0],[0,0],[-61.104,0],[0,15.769],[33.508,0]],"v":[[50.264,15.769],[50.264,0],[28.581,0],[-50.263,39.423],[-4.927,70.961]],"c":true}]}],"ix":2},"nm":"Path 1","mn":"ADBE Vector Shape - Group","hd":false},{"ind":1,"ty":"sh","ix":2,"ks":{"a":1,"k":[{"i":{"x":0,"y":1},"o":{"x":0.5,"y":0},"t":0,"s":[{"i":[[0,27.596],[-70.96,0],[0,0],[0,0],[27.596,0],[5.914,-17.741],[0,0],[-37.451,0],[0,-35.48],[0,0],[0,0],[0,0],[0,0],[39.422,0]],"o":[[0,-31.538],[0,0],[0,0],[0,-25.624],[-27.596,0],[0,0],[3.943,-25.625],[37.451,0],[0,0],[0,0],[0,0],[0,0],[0,0],[-39.423,0]],"v":[[-68.004,39.423],[28.581,-17.74],[50.264,-17.74],[50.264,-27.596],[4.928,-70.96],[-42.379,-39.422],[-60.119,-39.422],[4.928,-88.701],[68.004,-27.596],[68.004,86.73],[56.178,86.73],[50.264,61.105],[48.293,61.105],[-6.898,88.701]],"c":true}]},{"i":{"x":0,"y":1},"o":{"x":0.5,"y":0},"t":30,"s":[{"i":[[0.04,33.204],[-90.545,-0.383],[0,0],[0,0],[8.359,0.087],[5.914,-17.741],[0,0],[-41.912,-0.586],[-0.717,-40.027],[0,0],[0,0],[0,0],[0,0],[19.684,-0.074]],"o":[[-0.042,-34.546],[0,0],[0,0],[0,-25.624],[-9.52,-0.099],[0,0],[2.405,-33.326],[41.358,0.578],[0,0],[0,0],[0,0],[0,0],[0,0],[-39.318,0.147]],"v":[[-76.754,39.423],[31.831,-23.24],[31.264,-23.49],[31.514,-23.471],[2.928,-55.085],[-25.379,-35.797],[-70.869,-35.547],[4.928,-96.701],[77.004,-27.596],[76.754,86.48],[43.428,86.73],[35.764,69.855],[35.293,70.355],[-9.648,89.201]],"c":true}]},{"t":60,"s":[{"i":[[0,27.596],[-70.96,0],[0,0],[0,0],[27.596,0],[5.914,-17.741],[0,0],[-37.451,0],[0,-35.48],[0,0],[0,0],[0,0],[0,0],[39.422,0]],"o":[[0,-31.538],[0,0],[0,0],[0,-25.624],[-27.596,0],[0,0],[3.943,-25.625],[37.451,0],[0,0],[0,0],[0,0],[0,0],[0,0],[-39.423,0]],"v":[[-68.004,39.423],[28.581,-17.74],[50.264,-17.74],[50.264,-27.596],[4.928,-70.96],[-42.379,-39.422],[-60.119,-39.422],[4.928,-88.701],[68.004,-27.596],[68.004,86.73],[56.178,86.73],[50.264,61.105],[48.293,61.105],[-6.898,88.701]],"c":true}]}],"ix":2},"nm":"Path 2","mn":"ADBE Vector Shape - Group","hd":false},{"ty":"mm","mm":1,"nm":"Merge Paths 1","mn":"ADBE Vector Filter - Merge","hd":false},{"ty":"fl","c":{"a":0,"k":[1,1,1,1],"ix":4},"o":{"a":0,"k":100,"ix":5},"r":1,"bm":0,"nm":"Fill 1","mn":"ADBE Vector Graphic - Fill","hd":false},{"ty":"tr","p":{"a":0,"k":[68.254,88.951],"ix":2},"a":{"a":0,"k":[0,0],"ix":1},"s":{"a":0,"k":[100,100],"ix":3},"r":{"a":0,"k":0,"ix":6},"o":{"a":0,"k":100,"ix":7},"sk":{"a":0,"k":0,"ix":4},"sa":{"a":0,"k":0,"ix":5},"nm":"Transform"}],"nm":"Group 1","np":4,"cix":2,"bm":0,"ix":1,"mn":"ADBE Vector Group","hd":false}],"ip":0,"op":60,"st":0,"bm":0}],"markers":[]}